{
  "passed": false,
  "rows": [
    {
      "phase": "overall",
      "start_date": "2022-04-08",
      "end_date": "2024-10-02",
      "count": 23,
      "activated_trades": 23,
      "managed_expectancy": 0.400267,
      "gross_managed_expectancy": 0.58399,
      "profit_factor": 3.286979,
      "max_drawdown_r": 2.604982,
      "win_rate": 0.782609,
      "avg_execution_cost_r": 0.183723,
      "avg_funding_cost_r": 0.0,
      "avg_total_cost_r": 0.183723,
      "session_overtrade_count": 0,
      "passed": false,
      "failed_gates": "min_phase_trades;min_total_trades"
    },
    {
      "phase": "train",
      "start_date": "2022-04-08",
      "end_date": "2023-04-30",
      "count": 7,
      "activated_trades": 7,
      "managed_expectancy": 0.35565,
      "gross_managed_expectancy": 0.555392,
      "profit_factor": 2.660503,
      "max_drawdown_r": 1.469358,
      "win_rate": 0.714286,
      "avg_execution_cost_r": 0.199742,
      "avg_funding_cost_r": 0.0,
      "avg_total_cost_r": 0.199742,
      "session_overtrade_count": 0,
      "passed": false,
      "failed_gates": "min_phase_trades"
    },
    {
      "phase": "validation",
      "start_date": "2023-07-11",
      "end_date": "2024-03-12",
      "count": 8,
      "activated_trades": 8,
      "managed_expectancy": 0.34601,
      "gross_managed_expectancy": 0.495292,
      "profit_factor": 2.92744,
      "max_drawdown_r": 1.135624,
      "win_rate": 0.75,
      "avg_execution_cost_r": 0.149282,
      "avg_funding_cost_r": 0.0,
      "avg_total_cost_r": 0.149282,
      "session_overtrade_count": 0,
      "passed": false,
      "failed_gates": "min_phase_trades"
    },
    {
      "phase": "test",
      "start_date": "2024-03-12",
      "end_date": "2024-10-02",
      "count": 9,
      "activated_trades": 9,
      "managed_expectancy": 0.45518,
      "gross_managed_expectancy": 0.641462,
      "profit_factor": 4.758215,
      "max_drawdown_r": 1.090045,
      "win_rate": 0.888889,
      "avg_execution_cost_r": 0.186282,
      "avg_funding_cost_r": 0.0,
      "avg_total_cost_r": 0.186282,
      "session_overtrade_count": 0,
      "passed": false,
      "failed_gates": "min_phase_trades"
    }
  ]
}
