{
  "passed": false,
  "rows": [
    {
      "phase": "overall",
      "start_date": "2022-01-25",
      "end_date": "2024-10-02",
      "count": 91,
      "activated_trades": 91,
      "managed_expectancy": 0.203327,
      "gross_managed_expectancy": 0.34266,
      "profit_factor": 1.71838,
      "max_drawdown_r": 6.428901,
      "win_rate": 0.736264,
      "avg_execution_cost_r": 0.138921,
      "avg_funding_cost_r": 0.000412,
      "avg_total_cost_r": 0.139333,
      "session_overtrade_count": 0,
      "passed": false,
      "failed_gates": "min_managed_expectancy_r;min_profit_factor;min_total_trades"
    },
    {
      "phase": "train",
      "start_date": "2022-01-25",
      "end_date": "2023-02-28",
      "count": 30,
      "activated_trades": 30,
      "managed_expectancy": 0.255805,
      "gross_managed_expectancy": 0.369243,
      "profit_factor": 2.000818,
      "max_drawdown_r": 3.223882,
      "win_rate": 0.733333,
      "avg_execution_cost_r": 0.113543,
      "avg_funding_cost_r": -0.000105,
      "avg_total_cost_r": 0.113438,
      "session_overtrade_count": 0,
      "passed": false,
      "failed_gates": "min_managed_expectancy_r"
    },
    {
      "phase": "validation",
      "start_date": "2023-03-11",
      "end_date": "2023-11-30",
      "count": 30,
      "activated_trades": 30,
      "managed_expectancy": -0.030018,
      "gross_managed_expectancy": 0.127211,
      "profit_factor": 0.927678,
      "max_drawdown_r": 6.428901,
      "win_rate": 0.633333,
      "avg_execution_cost_r": 0.154356,
      "avg_funding_cost_r": 0.002873,
      "avg_total_cost_r": 0.157229,
      "session_overtrade_count": 0,
      "passed": false,
      "failed_gates": "min_managed_expectancy_r;min_profit_factor"
    },
    {
      "phase": "test",
      "start_date": "2023-12-06",
      "end_date": "2024-10-02",
      "count": 31,
      "activated_trades": 31,
      "managed_expectancy": 0.37836,
      "gross_managed_expectancy": 0.525433,
      "profit_factor": 3.080843,
      "max_drawdown_r": 1.504896,
      "win_rate": 0.83871,
      "avg_execution_cost_r": 0.148542,
      "avg_funding_cost_r": -0.001468,
      "avg_total_cost_r": 0.147074,
      "session_overtrade_count": 0,
      "passed": true,
      "failed_gates": ""
    }
  ]
}
