{
  "passed": false,
  "rows": [
    {
      "phase": "overall",
      "start_date": "2022-03-27",
      "end_date": "2026-04-20",
      "count": 50,
      "activated_trades": 50,
      "managed_expectancy": 0.384328,
      "gross_managed_expectancy": 0.561255,
      "profit_factor": 3.075631,
      "max_drawdown_r": 1.665064,
      "win_rate": 0.82,
      "avg_execution_cost_r": 0.176928,
      "avg_funding_cost_r": 0.0,
      "avg_total_cost_r": 0.176928,
      "session_overtrade_count": 0,
      "passed": false,
      "failed_gates": "min_managed_expectancy_r"
    },
    {
      "phase": "train",
      "start_date": "2022-03-27",
      "end_date": "2023-12-06",
      "count": 16,
      "activated_trades": 16,
      "managed_expectancy": 0.463054,
      "gross_managed_expectancy": 0.673907,
      "profit_factor": 3.881418,
      "max_drawdown_r": 1.497885,
      "win_rate": 0.8125,
      "avg_execution_cost_r": 0.210853,
      "avg_funding_cost_r": 0.0,
      "avg_total_cost_r": 0.210853,
      "session_overtrade_count": 0,
      "passed": true,
      "failed_gates": ""
    },
    {
      "phase": "validation",
      "start_date": "2024-02-16",
      "end_date": "2024-11-14",
      "count": 17,
      "activated_trades": 17,
      "managed_expectancy": 0.175977,
      "gross_managed_expectancy": 0.329815,
      "profit_factor": 1.68678,
      "max_drawdown_r": 1.665064,
      "win_rate": 0.764706,
      "avg_execution_cost_r": 0.153838,
      "avg_funding_cost_r": 0.0,
      "avg_total_cost_r": 0.153838,
      "session_overtrade_count": 0,
      "passed": false,
      "failed_gates": "min_managed_expectancy_r"
    },
    {
      "phase": "test",
      "start_date": "2024-12-10",
      "end_date": "2026-04-20",
      "count": 17,
      "activated_trades": 17,
      "managed_expectancy": 0.518582,
      "gross_managed_expectancy": 0.686671,
      "profit_factor": 4.782296,
      "max_drawdown_r": 1.232946,
      "win_rate": 0.882353,
      "avg_execution_cost_r": 0.168088,
      "avg_funding_cost_r": 0.0,
      "avg_total_cost_r": 0.168088,
      "session_overtrade_count": 0,
      "passed": true,
      "failed_gates": ""
    }
  ]
}
